{"cameraMode":{"drawMode":0,"name":"Shaded","section":"Shading Mode"},"sceneLighting":false,"audioPlay":false,"sceneViewState":{"showFog":true,"showMaterialUpdate":false,"showSkybox":false,"showFlares":true,"showImageEffects":true,"showParticleSystems":true},"in2DMode":false,"pivot":{"x":-550.14892578125,"y":13.205411911010743,"z":-253.64381408691407},"rotation":{"x":0.2409081906080246,"y":0.008731501176953316,"z":-0.0021637887693941595,"w":0.9705127477645874},"size":19.835756301879884,"orthographic":false}